{
  "generated_at": "2025-12-20T16:16:39.505Z",
  "link": "https://rina-vellichor.com/products/tutorial-miniature-wild-apples-on-a-branch-made-of-polymer-clay-and-air-dry-clay?variant=55455036408185",
  "image": "https://rina-vellichor.com/cdn/shop/files/eae69062-282f-4008-8d16-67e39b994840_2048x2048.jpg?v=1752371387",
  "title": "TUTORIAL Miniature wild apples on a branch made of polymer clay and air dry clay | PDF + video",
  "description": "The price includes a tutorial on creating a miniature wild apple tree using polymer clay and air dry clay for dollhouses at a scale of 1:12. This tutorial is a PDF file with a description of the necessary materials, a link to the video and text. For your convenience, the video is uploaded to YT and has subtitles in English. An active link to the video is inside the PDF file or via QR code. Please note that the video does not have voice acting! This tutorial is not suitable f…"
}