{
  "generated_at": "2026-01-22T20:18:52.134Z",
  "link": "https://rina-vellichor.com/products/template-miniature-br%D0%B0mbly-hedge-book-the-secret-stairc%D0%B0se?variant=55455039816057",
  "image": "https://rina-vellichor.com/cdn/shop/files/25a44621-ddc2-487b-87bb-cf51c72fbfe4_2048x2048.jpg?v=1752371568",
  "title": "TEMPLATE Miniature Brаmbly Hedge book The Secret Staircаse | PDF",
  "description": "The book is designed for paper weight 80 gsm. Examples were printed on self-adhesive photo paper with a density of 80 g/m2 in the mode for printing photographs with the highest quality on an inkjet printer. If you use thicker paper, there is a chance that the book will not close. Therefore, I recommend that you use a hair straightening iron.Please note that the templates are made in 1:12 scale and do not have other sizes. When printed, the text is practically unreadable. The…"
}